{".class": "MypyFile", "_fullname": "torch.ao.sparsity.experimental.pruner.parametrization", "is_partial_stub_package": false, "is_stub": false, "names": {".class": "SymbolTable", "ActivationReconstruction": {".class": "SymbolTableNode", "kind": "Gdef", "node": {".class": "TypeInfo", "_promote": null, "abstract_attributes": [], "bases": ["builtins.object"], "declared_metaclass": null, "defn": {".class": "ClassDef", "fullname": "torch.ao.sparsity.experimental.pruner.parametrization.ActivationReconstruction", "name": "ActivationReconstruction", "type_vars": []}, "flags": [], "fullname": "torch.ao.sparsity.experimental.pruner.parametrization.ActivationReconstruction", "metaclass_type": null, "metadata": {}, "module_name": "torch.ao.sparsity.experimental.pruner.parametrization", "mro": ["torch.ao.sparsity.experimental.pruner.parametrization.ActivationReconstruction", "builtins.object"], "names": {".class": "SymbolTable", "__call__": {".class": "SymbolTableNode", "kind": "Mdef", "node": {".class": "FuncDef", "arg_kinds": [0, 0, 0, 0], "arg_names": ["self", "module", "input", "output"], "flags": [], "fullname": "torch.ao.sparsity.experimental.pruner.parametrization.ActivationReconstruction.__call__", "name": "__call__", "type": null}}, "__init__": {".class": "SymbolTableNode", "kind": "Mdef", "node": {".class": "FuncDef", "arg_kinds": [0, 0], "arg_names": ["self", "parametrization"], "flags": [], "fullname": "torch.ao.sparsity.experimental.pruner.parametrization.ActivationReconstruction.__init__", "name": "__init__", "type": null}}, "param": {".class": "SymbolTableNode", "implicit": true, "kind": "Mdef", "node": {".class": "Var", "flags": [], "fullname": "torch.ao.sparsity.experimental.pruner.parametrization.ActivationReconstruction.param", "name": "param", "type": {".class": "AnyType", "missing_import_name": null, "source_any": null, "type_of_any": 1}}}}, "tuple_type": null, "type_vars": [], "typeddict_type": null}}, "Any": {".class": "SymbolTableNode", "cross_ref": "typing.Any", "kind": "Gdef"}, "BiasHook": {".class": "SymbolTableNode", "kind": "Gdef", "node": {".class": "TypeInfo", "_promote": null, "abstract_attributes": [], "bases": ["builtins.object"], "declared_metaclass": null, "defn": {".class": "ClassDef", "fullname": "torch.ao.sparsity.experimental.pruner.parametrization.BiasHook", "name": "BiasHook", "type_vars": []}, "flags": [], "fullname": "torch.ao.sparsity.experimental.pruner.parametrization.BiasHook", "metaclass_type": null, "metadata": {}, "module_name": "torch.ao.sparsity.experimental.pruner.parametrization", "mro": ["torch.ao.sparsity.experimental.pruner.parametrization.BiasHook", "builtins.object"], "names": {".class": "SymbolTable", "__call__": {".class": "SymbolTableNode", "kind": "Mdef", "node": {".class": "FuncDef", "arg_kinds": [0, 0, 0, 0], "arg_names": ["self", "module", "input", "output"], "flags": [], "fullname": "torch.ao.sparsity.experimental.pruner.parametrization.BiasHook.__call__", "name": "__call__", "type": null}}, "__init__": {".class": "SymbolTableNode", "kind": "Mdef", "node": {".class": "FuncDef", "arg_kinds": [0, 0, 0], "arg_names": ["self", "parametrization", "prune_bias"], "flags": [], "fullname": "torch.ao.sparsity.experimental.pruner.parametrization.BiasHook.__init__", "name": "__init__", "type": null}}, "param": {".class": "SymbolTableNode", "implicit": true, "kind": "Mdef", "node": {".class": "Var", "flags": [], "fullname": "torch.ao.sparsity.experimental.pruner.parametrization.BiasHook.param", "name": "param", "type": {".class": "AnyType", "missing_import_name": null, "source_any": null, "type_of_any": 1}}}, "prune_bias": {".class": "SymbolTableNode", "implicit": true, "kind": "Mdef", "node": {".class": "Var", "flags": [], "fullname": "torch.ao.sparsity.experimental.pruner.parametrization.BiasHook.prune_bias", "name": "prune_bias", "type": {".class": "AnyType", "missing_import_name": null, "source_any": null, "type_of_any": 1}}}}, "tuple_type": null, "type_vars": [], "typeddict_type": null}}, "List": {".class": "SymbolTableNode", "cross_ref": "typing.List", "kind": "Gdef"}, "PruningParametrization": {".class": "SymbolTableNode", "kind": "Gdef", "node": {".class": "TypeInfo", "_promote": null, "abstract_attributes": [], "bases": ["torch.nn.modules.module.Module"], "declared_metaclass": null, "defn": {".class": "ClassDef", "fullname": "torch.ao.sparsity.experimental.pruner.parametrization.PruningParametrization", "name": "PruningParametrization", "type_vars": []}, "flags": [], "fullname": "torch.ao.sparsity.experimental.pruner.parametrization.PruningParametrization", "metaclass_type": null, "metadata": {}, "module_name": "torch.ao.sparsity.experimental.pruner.parametrization", "mro": ["torch.ao.sparsity.experimental.pruner.parametrization.PruningParametrization", "torch.nn.modules.module.Module", "builtins.object"], "names": {".class": "SymbolTable", "__init__": {".class": "SymbolTableNode", "kind": "Mdef", "node": {".class": "FuncDef", "arg_kinds": [0, 0], "arg_names": ["self", "original_outputs"], "flags": [], "fullname": "torch.ao.sparsity.experimental.pruner.parametrization.PruningParametrization.__init__", "name": "__init__", "type": null}}, "forward": {".class": "SymbolTableNode", "kind": "Mdef", "node": {".class": "FuncDef", "arg_kinds": [0, 0], "arg_names": ["self", "x"], "flags": [], "fullname": "torch.ao.sparsity.experimental.pruner.parametrization.PruningParametrization.forward", "name": "forward", "type": null}}, "original_outputs": {".class": "SymbolTableNode", "implicit": true, "kind": "Mdef", "node": {".class": "Var", "flags": [], "fullname": "torch.ao.sparsity.experimental.pruner.parametrization.PruningParametrization.original_outputs", "name": "original_outputs", "type": {".class": "AnyType", "missing_import_name": null, "source_any": null, "type_of_any": 1}}}, "pruned_outputs": {".class": "SymbolTableNode", "implicit": true, "kind": "Mdef", "node": {".class": "Var", "flags": [], "fullname": "torch.ao.sparsity.experimental.pruner.parametrization.PruningParametrization.pruned_outputs", "name": "pruned_outputs", "type": {".class": "AnyType", "missing_import_name": null, "source_any": null, "type_of_any": 1}}}}, "tuple_type": null, "type_vars": [], "typeddict_type": null}}, "ZeroesParametrization": {".class": "SymbolTableNode", "kind": "Gdef", "node": {".class": "TypeInfo", "_promote": null, "abstract_attributes": [], "bases": ["torch.nn.modules.module.Module"], "declared_metaclass": null, "defn": {".class": "ClassDef", "fullname": "torch.ao.sparsity.experimental.pruner.parametrization.ZeroesParametrization", "name": "ZeroesParametrization", "type_vars": []}, "flags": [], "fullname": "torch.ao.sparsity.experimental.pruner.parametrization.ZeroesParametrization", "metaclass_type": null, "metadata": {}, "module_name": "torch.ao.sparsity.experimental.pruner.parametrization", "mro": ["torch.ao.sparsity.experimental.pruner.parametrization.ZeroesParametrization", "torch.nn.modules.module.Module", "builtins.object"], "names": {".class": "SymbolTable", "__init__": {".class": "SymbolTableNode", "kind": "Mdef", "node": {".class": "FuncDef", "arg_kinds": [0, 0], "arg_names": ["self", "original_outputs"], "flags": [], "fullname": "torch.ao.sparsity.experimental.pruner.parametrization.ZeroesParametrization.__init__", "name": "__init__", "type": null}}, "forward": {".class": "SymbolTableNode", "kind": "Mdef", "node": {".class": "FuncDef", "arg_kinds": [0, 0], "arg_names": ["self", "x"], "flags": [], "fullname": "torch.ao.sparsity.experimental.pruner.parametrization.ZeroesParametrization.forward", "name": "forward", "type": null}}, "original_outputs": {".class": "SymbolTableNode", "implicit": true, "kind": "Mdef", "node": {".class": "Var", "flags": [], "fullname": "torch.ao.sparsity.experimental.pruner.parametrization.ZeroesParametrization.original_outputs", "name": "original_outputs", "type": {".class": "AnyType", "missing_import_name": null, "source_any": null, "type_of_any": 1}}}, "pruned_outputs": {".class": "SymbolTableNode", "implicit": true, "kind": "Mdef", "node": {".class": "Var", "flags": [], "fullname": "torch.ao.sparsity.experimental.pruner.parametrization.ZeroesParametrization.pruned_outputs", "name": "pruned_outputs", "type": {".class": "AnyType", "missing_import_name": null, "source_any": null, "type_of_any": 1}}}}, "tuple_type": null, "type_vars": [], "typeddict_type": null}}, "__doc__": {".class": "SymbolTableNode", "kind": "Gdef", "node": {".class": "Var", "flags": ["is_ready"], "fullname": "torch.ao.sparsity.experimental.pruner.parametrization.__doc__", "name": "__doc__", "type": "builtins.str"}}, "__file__": {".class": "SymbolTableNode", "kind": "Gdef", "node": {".class": "Var", "flags": ["is_ready"], "fullname": "torch.ao.sparsity.experimental.pruner.parametrization.__file__", "name": "__file__", "type": "builtins.str"}}, "__name__": {".class": "SymbolTableNode", "kind": "Gdef", "node": {".class": "Var", "flags": ["is_ready"], "fullname": "torch.ao.sparsity.experimental.pruner.parametrization.__name__", "name": "__name__", "type": "builtins.str"}}, "__package__": {".class": "SymbolTableNode", "kind": "Gdef", "node": {".class": "Var", "flags": ["is_ready"], "fullname": "torch.ao.sparsity.experimental.pruner.parametrization.__package__", "name": "__package__", "type": "builtins.str"}}, "nn": {".class": "SymbolTableNode", "cross_ref": "torch.nn", "kind": "Gdef"}, "torch": {".class": "SymbolTableNode", "cross_ref": "torch", "kind": "Gdef"}}, "path": "/Users/toru/.pyenv/versions/3.9.4/lib/python3.9/site-packages/torch/ao/sparsity/experimental/pruner/parametrization.py"}